dynatademand/__init__.py
dynatademand/api.py
dynatademand/errors.py
dynatademand/schemas/request/body/buy_project.json
dynatademand/schemas/request/body/create_line_item.json
dynatademand/schemas/request/body/create_project.json
dynatademand/schemas/request/body/create_template.json
dynatademand/schemas/request/body/logout.json
dynatademand/schemas/request/body/obtain_access_token.json
dynatademand/schemas/request/body/reconcile_project.json
dynatademand/schemas/request/body/refresh_access_token.json
dynatademand/schemas/request/body/update_line_item.json
dynatademand/schemas/request/body/update_project.json
dynatademand/schemas/request/body/update_template.json
dynatademand/schemas/request/body/upsert_project_permissions.json
dynatademand/schemas/request/path/buy_project.json
dynatademand/schemas/request/path/close_line_item.json
dynatademand/schemas/request/path/close_project.json
dynatademand/schemas/request/path/create_line_item.json
dynatademand/schemas/request/path/create_template.json
dynatademand/schemas/request/path/delete_template.json
dynatademand/schemas/request/path/get_attributes.json
dynatademand/schemas/request/path/get_event.json
dynatademand/schemas/request/path/get_feasibility.json
dynatademand/schemas/request/path/get_invoice.json
dynatademand/schemas/request/path/get_line_item.json
dynatademand/schemas/request/path/get_line_item_detailed_report.json
dynatademand/schemas/request/path/get_line_items.json
dynatademand/schemas/request/path/get_project.json
dynatademand/schemas/request/path/get_project_detailed_report.json
dynatademand/schemas/request/path/get_project_permissions.json
dynatademand/schemas/request/path/get_templates.json
dynatademand/schemas/request/path/launch_line_item.json
dynatademand/schemas/request/path/pause_line_item.json
dynatademand/schemas/request/path/reconcile_project.json
dynatademand/schemas/request/path/set_quotacell_status.json
dynatademand/schemas/request/path/update_line_item.json
dynatademand-1.0.5.dist-info/LICENSE
dynatademand-1.0.5.dist-info/WHEEL
dynatademand-1.0.5.dist-info/METADATA
dynatademand-1.0.5.dist-info/RECORD
