Metadata-Version: 2.1
Name: dynatademand
Version: 1.0.5
Summary: A Python client library for the Dynata Demand API
Home-page: https://github.com/dynata/python-demandapi-client
Author: Ridley Larsen
Author-email: Ridley.Larsen@dynata.com
Requires-Python: >=2.7, !=3.0.*, !=3.1.*, !=3.2.*, !=3.3.*, !=3.4.*
Classifier: Programming Language :: Python :: 2
Classifier: Programming Language :: Python :: 2.7
Classifier: Programming Language :: Python :: 3
Classifier: Programming Language :: Python :: 3.5
Classifier: Programming Language :: Python :: 3.6
Classifier: Programming Language :: Python :: 3.7
Classifier: Programming Language :: Python :: 3.8
Requires-Dist: jsonschema (==3.2.0)
Requires-Dist: requests (==2.22.0)
Project-URL: Repository, https://github.com/dynata/python-demandapi-client
